demomcpserver_lxw/__init__.py
demomcpserver_lxw/server.py
demomcpserver_lxw-0.1.3.dist-info/METADATA
demomcpserver_lxw-0.1.3.dist-info/WHEEL
demomcpserver_lxw-0.1.3.dist-info/entry_points.txt
demomcpserver_lxw-0.1.3.dist-info/RECORD
