Metadata-Version: 2.4
Name: demomcpserver-lxw
Version: 0.1.3
Summary: Add your description here
Author-email: Liyu Wang <liyu.wang@resmed.com>
Requires-Python: >=3.12
Requires-Dist: fastmcp>=2.13.0.2
